dementor/__init__.py
dementor/__main__.py
dementor/filters.py
dementor/loader.py
dementor/paths.py
dementor/servers.py
dementor/standalone.py
dementor/assets/Dementor.toml
dementor/assets/banner.txt
dementor/assets/www/error_page.html
dementor/assets/www/wpad.dat
dementor/assets/www/upnp-default/dd.xml
dementor/assets/www/upnp-default/present.html
dementor/assets/www/upnp-default/scpd.xml
dementor/config/__init__.py
dementor/config/attr.py
dementor/config/session.py
dementor/config/toml.py
dementor/config/util.py
dementor/db/__init__.py
dementor/db/connector.py
dementor/db/model.py
dementor/log/__init__.py
dementor/log/hexdump.py
dementor/log/logger.py
dementor/log/stream.py
dementor/protocols/__init__.py
dementor/protocols/ftp.py
dementor/protocols/http.py
dementor/protocols/imap.py
dementor/protocols/ipp.py
dementor/protocols/kerberos.py
dementor/protocols/ldap.py
dementor/protocols/llmnr.py
dementor/protocols/mdns.py
dementor/protocols/msrpc.py
dementor/protocols/mssql.py
dementor/protocols/mysql.py
dementor/protocols/netbios.py
dementor/protocols/ntlm.py
dementor/protocols/pop3.py
dementor/protocols/quic.py
dementor/protocols/smb.py
dementor/protocols/smtp.py
dementor/protocols/spnego.py
dementor/protocols/ssdp.py
dementor/protocols/upnp.py
dementor/protocols/x11.py
dementor/protocols/msrpc/__init__.py
dementor/protocols/msrpc/dcom.py
dementor/protocols/msrpc/epm.py
dementor/protocols/msrpc/rpc.py
dementor-1.0.0.dev16.dist-info/licenses/LICENSE
dementor-1.0.0.dev16.dist-info/METADATA
dementor-1.0.0.dev16.dist-info/WHEEL
dementor-1.0.0.dev16.dist-info/entry_points.txt
dementor-1.0.0.dev16.dist-info/top_level.txt
dementor-1.0.0.dev16.dist-info/RECORD
