Metadata-Version: 2.4
Name: dementor
Version: 1.0.0.dev16
Summary: LLMNR/NBT-NS/mDNS Poisoner and rogue service provider
Author: MatrixEditor
Maintainer: MatrixEditor
License: The MIT License (MIT)
Project-URL: homepage, https://matrixeditor.github.io/dementor
Project-URL: documentation, https://matrixeditor.github.io/dementor
Project-URL: source, https://github.com/MatrixEditor/dementor
Classifier: Development Status :: 4 - Beta
Classifier: Intended Audience :: Developers
Classifier: Intended Audience :: Science/Research
Classifier: License :: OSI Approved :: MIT License
Classifier: Programming Language :: Python :: 3
Classifier: Programming Language :: Python :: 3.13
Classifier: Programming Language :: Python :: 3 :: Only
Classifier: Programming Language :: Python :: Implementation :: CPython
Classifier: Topic :: Security
Classifier: Topic :: System :: Networking
Classifier: Typing :: Typed
Classifier: Operating System :: POSIX
Classifier: Operating System :: Unix
License-File: LICENSE
Requires-Dist: rich
Requires-Dist: impacket
Requires-Dist: scapy
Requires-Dist: aiosmtpd
Requires-Dist: sqlalchemy
Requires-Dist: pyasn1
Requires-Dist: aioquic
Requires-Dist: typer
Requires-Dist: jinja2
Requires-Dist: caterpillar-py
Requires-Dist: pyipp
Dynamic: license-file
